{
	"pageElement": {
		"id": "bed6b79b-3cf6-6119-c4a9-118de53c3b44",
		"pageElements": [
			{
				"definition": {
					"fragmentStyle": {
						"backgroundColor": "colorBrandPrimary",
						"paddingBottom": "5",
						"paddingLeft": "5",
						"paddingRight": "5",
						"paddingTop": "5"
					},
					"indexed": true,
					"layout": {
						"align": "Center",
						"contentDisplay": "FlexColumn",
						"justify": "Center",
						"paddingBottom": 4,
						"paddingLeft": 4,
						"paddingRight": 4,
						"paddingTop": 4
					},
					"name": "Banner"
				},
				"id": "3b7a0b4d-9323-88d8-f991-50f8f814d005",
				"pageElements": [
					{
						"definition": {
							"fragment": {
								"key": "cp-welcome-text",
								"siteKey": "Customer Portal"
							},
							"fragmentConfig": {
							},
							"fragmentFields": [
							],
							"fragmentStyle": {
								"textColor": "colorNeutral0"
							},
							"indexed": true
						},
						"id": "e8cafae4-d9a0-a545-52f6-e11d21911549",
						"type": "Fragment"
					},
					{
						"definition": {
							"fragmentStyle": {
								"maxWidth": "var(--container-max-lg)",
								"width": "100%"
							},
							"widgetInstance": {
								"widgetConfig": {
									"destination": "",
									"displayStyle": "ddmTemplate_SEARCH-BAR-LEFT-ALIGNED-ICON-FTL",
									"displayStyleGroupId": "20121",
									"displayStyleGroupKey": "19497231034269",
									"federatedSearchKey": "",
									"invisible": "false",
									"keywordsParameterName": "q",
									"scopeParameterName": "scope",
									"searchScope": "this-site",
									"showStagedResults": "false",
									"suggestionsContributorConfigurations": "{\"contributorName\": \"basic\", \"displayGroupName\": \"suggestions\", \"size\": 5}",
									"suggestionsDisplayThreshold": "2",
									"suggestionsEnabled": "true",
									"useAdvancedSearchSyntax": "false"
								},
								"widgetName": "com_liferay_portal_search_web_search_bar_portlet_SearchBarPortlet"
							}
						},
						"id": "96511b43-e059-379f-7b39-3f0d213d7951",
						"type": "Widget"
					}
				],
				"type": "Section"
			},
			{
				"definition": {
					"fragmentStyle": {
						"maxWidth": "var(--container-max-xl)",
						"paddingBottom": "4",
						"paddingLeft": "5",
						"paddingRight": "5",
						"paddingTop": "4"
					},
					"indexed": true,
					"layout": {
						"paddingBottom": 2,
						"paddingLeft": 4,
						"paddingRight": 4,
						"paddingTop": 2,
						"widthType": "Fixed"
					},
					"name": "Content"
				},
				"id": "9f6dba6e-63c5-964f-9795-a7da9651262a",
				"pageElements": [
					{
						"definition": {
							"fragment": {
								"key": "cp-layout",
								"siteKey": "Customer Portal"
							},
							"fragmentConfig": {
								"alignDesktop": "center",
								"alignMobile": "flex-start",
								"alignTablet": "flex-start",
								"directionDesktop": "row",
								"directionMobile": "row",
								"directionTablet": "row",
								"distributeDesktop": "space-between",
								"distributeMobile": "flex-start",
								"distributeTablet": "flex-start",
								"fillHeightDesktop": true,
								"fillHeightMobile": false,
								"fillHeightTablet": true,
								"horizontalGapDesktop": "var(--spacer-4)",
								"horizontalGapMobile": "var(--spacer-3)",
								"horizontalGapTablet": "var(--spacer-4)",
								"verticalGapDesktop": "var(--spacer-4)",
								"verticalGapMobile": "var(--spacer-3)",
								"verticalGapTablet": "var(--spacer-4)",
								"widthBasisDesktop": "1",
								"widthBasisMobile": "1",
								"widthBasisTablet": "50%",
								"widthDesktop": "auto",
								"widthGrowDesktop": "1",
								"widthGrowMobile": "1",
								"widthGrowTablet": "1",
								"widthMobile": "auto",
								"widthTablet": "auto",
								"wrapDesktop": "nowrap",
								"wrapMobile": "nowrap",
								"wrapTablet": "nowrap"
							},
							"fragmentFields": [
							],
							"fragmentStyle": {
								"marginBottom": "4"
							},
							"indexed": true
						},
						"id": "479f5070-d87e-1972-ee4e-b8deecdd0703",
						"pageElements": [
							{
								"definition": {
								},
								"id": "988f4a3c-71c0-0aa1-4c98-1d47f38317ef",
								"pageElements": [
									{
										"definition": {
											"cssClasses": [
												"card",
												"card-flat"
											],
											"fragmentLink": {
												"href": {
													"value_i18n": {
														"en_US": "https://learn.liferay.com"
													}
												}
											},
											"fragmentStyle": {
												"backgroundColor": "colorBrandPrimaryLighten5",
												"borderRadius": "borderRadiusLg",
												"paddingBottom": "4",
												"paddingLeft": "4",
												"paddingRight": "4",
												"paddingTop": "4",
												"textAlign": "center"
											},
											"indexed": true,
											"layout": {
												"align": "Center",
												"contentDisplay": "FlexColumn",
												"justify": "Center",
												"paddingBottom": 2,
												"paddingLeft": 2,
												"paddingRight": 2,
												"paddingTop": 2
											}
										},
										"id": "163a8c1c-6e88-bdf0-06ee-c1a6c7633f94",
										"pageElements": [
											{
												"definition": {
													"fragment": {
														"key": "BASIC_COMPONENT-html"
													},
													"fragmentConfig": {
													},
													"fragmentFields": [
														{
															"id": "element-html",
															"value": {
																"html": {
																	"value_i18n": {
																		"en_US": "<svg width=\"48\" height=\"48\" viewBox=\"0 0 48 48\" fill=\"none\" xmlns=\"http://www.w3.org/2000/svg\">\n<path d=\"M46.2198 17.331L23.9998 30.671L1.77979 17.331L23.9998 4.00098L46.2198 17.331Z\" fill=\"currentColor\" stroke=\"currentColor\" stroke-width=\"2\" stroke-linecap=\"round\" stroke-linejoin=\"round\"/>\n<path d=\"M39.5601 21.3809V32.8909\" stroke=\"currentColor\" stroke-width=\"2\" stroke-linecap=\"round\" stroke-linejoin=\"round\"/>\n<path d=\"M39.5599 32.8909V35.1109C39.5599 40.0209 32.5999 44.0009 23.9999 44.0009C15.3999 44.0009 8.43994 40.0209 8.43994 35.1109V21.3809\" stroke=\"currentColor\" stroke-width=\"2\" stroke-linecap=\"round\" stroke-linejoin=\"round\"/>\n<path d=\"M32.8901 35.1109V26.2209\" stroke=\"currentColor\" stroke-width=\"2\" stroke-linecap=\"round\" stroke-linejoin=\"round\"/>\n</svg>\n"
																	}
																}
															}
														}
													],
													"fragmentStyle": {
														"height": "48px",
														"textColor": "colorBrandPrimary",
														"width": "48px"
													},
													"indexed": true
												},
												"id": "f561c1e4-04cc-1034-ae52-1d0fd2a58470",
												"type": "Fragment"
											},
											{
												"definition": {
													"fragment": {
														"key": "cp-text",
														"siteKey": "Customer Portal"
													},
													"fragmentConfig": {
														"textType": "h5",
														"truncateText": false
													},
													"fragmentFields": [
														{
															"id": "element-text",
															"value": {
																"fragmentLink": {
																},
																"text": {
																	"value_i18n": {
																		"en_US": "Liferay Learn"
																	}
																}
															}
														}
													],
													"fragmentStyle": {
														"marginBottom": "2",
														"marginTop": "2"
													},
													"indexed": true
												},
												"id": "cf6ac19c-4b90-504d-4a43-dd206c650bdd",
												"type": "Fragment"
											},
											{
												"definition": {
													"fragment": {
														"key": "cp-text",
														"siteKey": "Customer Portal"
													},
													"fragmentConfig": {
														"textType": "text-paragraph",
														"truncateText": false
													},
													"fragmentFields": [
														{
															"id": "element-text",
															"value": {
																"fragmentLink": {
																},
																"text": {
																	"value_i18n": {
																		"en_US": "Find documentation, tutorials, and guides."
																	}
																}
															}
														}
													],
													"indexed": true
												},
												"id": "d4395897-ea4d-7fbd-6630-9281d6abd4be",
												"type": "Fragment"
											}
										],
										"type": "Section"
									},
									{
										"definition": {
											"cssClasses": [
												"card",
												"card-flat"
											],
											"fragmentStyle": {
												"backgroundColor": "colorBrandPrimaryLighten5",
												"borderRadius": "borderRadiusLg",
												"paddingBottom": "4",
												"paddingLeft": "4",
												"paddingRight": "4",
												"paddingTop": "4",
												"textAlign": "center"
											},
											"indexed": true,
											"layout": {
												"align": "Center",
												"contentDisplay": "FlexColumn",
												"justify": "Center",
												"paddingBottom": 2,
												"paddingLeft": 2,
												"paddingRight": 2,
												"paddingTop": 2
											}
										},
										"id": "68cda6f4-eb6c-49c1-987e-92ca52d6ff0d",
										"pageElements": [
											{
												"definition": {
													"fragment": {
														"key": "BASIC_COMPONENT-html"
													},
													"fragmentConfig": {
													},
													"fragmentFields": [
														{
															"id": "element-html",
															"value": {
																"html": {
																	"value_i18n": {
																		"en_US": "<svg width=\"48\" height=\"48\" viewBox=\"0 0 48 48\" fill=\"none\" xmlns=\"http://www.w3.org/2000/svg\">\n<g clip-path=\"url(#clip0_3059_9382)\">\n<g style=\"mix-blend-mode:multiply\">\n<path d=\"M24 46.5149H24.0225C41.8086 40.2335 42 20.196 42 10.0647C36.0788 10.5938 27.7711 8.01589 24.0112 1.48682H23.9887C20.2289 8.01589 11.9212 10.605 6 10.0647C6 20.196 6.19137 40.2223 23.9775 46.5149H24V46.5149Z\" stroke=\"#0B5FFF\" stroke-width=\"2\" stroke-miterlimit=\"10\"/>\n</g>\n<path d=\"M24.0001 35.6968C29.0608 35.6968 33.1634 31.5943 33.1634 26.5336C33.1634 21.4729 29.0608 17.3704 24.0001 17.3704C18.9394 17.3704 14.8369 21.4729 14.8369 26.5336C14.8369 31.5943 18.9394 35.6968 24.0001 35.6968Z\" fill=\"#0B5FFF\" stroke=\"#0B5FFF\" stroke-width=\"2\" stroke-miterlimit=\"10\" stroke-linecap=\"round\"/>\n<path d=\"M20.2065 26.5338L22.7394 29.0666L27.7938 24.001\" stroke=\"#F1F5FB\" stroke-width=\"2\" stroke-linecap=\"round\" stroke-linejoin=\"round\"/>\n</g>\n<defs>\n<clipPath id=\"clip0_3059_9382\">\n<rect width=\"48\" height=\"48\" fill=\"white\" transform=\"translate(0 0.000976562)\"/>\n</clipPath>\n</defs>\n</svg>\n"
																	}
																}
															}
														}
													],
													"fragmentStyle": {
														"height": "48px",
														"textColor": "colorBrandPrimary",
														"width": "48px"
													},
													"indexed": true
												},
												"id": "6a95cdc1-f8bc-909f-dd65-a67d520b3999",
												"type": "Fragment"
											},
											{
												"definition": {
													"fragment": {
														"key": "cp-text",
														"siteKey": "Customer Portal"
													},
													"fragmentConfig": {
														"textType": "h5",
														"truncateText": false
													},
													"fragmentFields": [
														{
															"id": "element-text",
															"value": {
																"fragmentLink": {
																},
																"text": {
																	"value_i18n": {
																		"en_US": "Security Reports"
																	}
																}
															}
														}
													],
													"fragmentStyle": {
														"marginBottom": "2",
														"marginTop": "2"
													},
													"indexed": true
												},
												"id": "f43296f9-1ba3-7942-15c5-8e91e6784301",
												"type": "Fragment"
											},
											{
												"definition": {
													"fragment": {
														"key": "cp-text",
														"siteKey": "Customer Portal"
													},
													"fragmentConfig": {
														"textType": "text-paragraph",
														"truncateText": false
													},
													"fragmentFields": [
														{
															"id": "element-text",
															"value": {
																"fragmentLink": {
																},
																"text": {
																	"value_i18n": {
																		"en_US": "Latest vulnerability alerts and incident updates."
																	}
																}
															}
														}
													],
													"indexed": true
												},
												"id": "64597dc1-9fa1-fe30-77dc-6fceb1c198e9",
												"type": "Fragment"
											}
										],
										"type": "Section"
									},
									{
										"definition": {
											"cssClasses": [
												"card",
												"card-flat"
											],
											"fragmentStyle": {
												"backgroundColor": "colorBrandPrimaryLighten5",
												"borderRadius": "borderRadiusLg",
												"paddingBottom": "4",
												"paddingLeft": "4",
												"paddingRight": "4",
												"paddingTop": "4",
												"textAlign": "center"
											},
											"indexed": true,
											"layout": {
												"align": "Center",
												"contentDisplay": "FlexColumn",
												"justify": "Center",
												"paddingBottom": 2,
												"paddingLeft": 2,
												"paddingRight": 2,
												"paddingTop": 2
											}
										},
										"id": "19e6bc21-9467-55ab-c8e6-46425c1099bc",
										"pageElements": [
											{
												"definition": {
													"fragment": {
														"key": "BASIC_COMPONENT-html"
													},
													"fragmentConfig": {
													},
													"fragmentFields": [
														{
															"id": "element-html",
															"value": {
																"html": {
																	"value_i18n": {
																		"en_US": "<svg width=\"48\" height=\"48\" viewBox=\"0 0 48 48\" fill=\"none\" xmlns=\"http://www.w3.org/2000/svg\">\n<path d=\"M21 21.001H33M21 27.001H33M21 33.001H33\" stroke=\"currentColor\" stroke-width=\"2\" stroke-linecap=\"round\"/>\n<path d=\"M17 19.001H15C14.4477 19.001 14 19.4487 14 20.001V22.001C14 22.5533 14.4477 23.001 15 23.001H17C17.5523 23.001 18 22.5533 18 22.001V20.001C18 19.4487 17.5523 19.001 17 19.001Z\" fill=\"currentColor\"/>\n<path d=\"M17 25.001H15C14.4477 25.001 14 25.4487 14 26.001V28.001C14 28.5533 14.4477 29.001 15 29.001H17C17.5523 29.001 18 28.5533 18 28.001V26.001C18 25.4487 17.5523 25.001 17 25.001Z\" fill=\"currentColor\"/>\n<path d=\"M17 31.001H15C14.4477 31.001 14 31.4487 14 32.001V34.001C14 34.5533 14.4477 35.001 15 35.001H17C17.5523 35.001 18 34.5533 18 34.001V32.001C18 31.4487 17.5523 31.001 17 31.001Z\" fill=\"currentColor\"/>\n<path d=\"M10 15.0011H19V5.62109\" fill=\"currentColor\"/>\n<path d=\"M10 15.0011H19V5.62109\" stroke=\"currentColor\" stroke-width=\"2\" stroke-linecap=\"round\" stroke-linejoin=\"round\"/>\n<path d=\"M38.0098 11.1506V41.261C38.0098 42.7403 36.8252 43.9914 35.3203 43.9915H11.6807L11.4023 43.9768C10.0319 43.8342 8.99023 42.648 8.99023 41.261V41.0012H10.9902V41.261C10.9902 41.6816 11.3256 41.9915 11.6807 41.9915H35.3203C35.6753 41.9914 36.0098 41.6816 36.0098 41.261V11.1506H38.0098ZM10.9902 39.9631H8.99023V37.887H10.9902V39.9631ZM35.3203 4.01099C36.8252 4.01103 38.0098 5.26214 38.0098 6.74146V7.00122H36.0098V6.74146C36.0098 6.32082 35.6753 6.01103 35.3203 6.01099H19.7012L10.9902 14.9182V36.8499H8.99023V14.511C8.99023 14.2496 9.09267 13.9986 9.27539 13.8118L18.5654 4.31177L18.6387 4.24341C18.8177 4.09374 19.0448 4.01099 19.2803 4.01099H35.3203ZM38.0098 10.1135H36.0098V8.03833H38.0098V10.1135Z\" fill=\"currentColor\"/>\n<path d=\"M21.9237 37.8874H8.43129C6.7084 37.8874 5.31764 36.4966 5.31764 34.7738V33.7774H6.98863C7.3934 33.7774 7.65287 33.3415 7.4453 32.9886L4.73643 28.2974C4.52885 27.9445 4.03067 27.9445 3.82309 28.2974L1.11422 32.9886C0.906643 33.3415 1.16611 33.7774 1.57089 33.7774H3.24188V34.7738C3.24188 37.6383 5.56673 39.9632 8.43129 39.9632H21.9237C22.4946 39.9632 22.9616 39.4961 22.9616 38.9253C22.9616 38.3544 22.4946 37.8874 21.9237 37.8874Z\" fill=\"currentColor\"/>\n<path d=\"M24.8851 10.1132H38.3716C40.0937 10.1132 41.4838 11.5033 41.4838 13.2254V14.2214H39.8136C39.409 14.2214 39.1496 14.6571 39.3571 15.0098L42.0648 19.6989C42.2723 20.0517 42.7702 20.0517 42.9777 19.6989L45.6854 15.0098C45.8929 14.6571 45.6335 14.2214 45.2289 14.2214H43.5587V13.2254C43.5587 10.3622 41.2348 8.03833 38.3716 8.03833H24.8851C24.3145 8.03833 23.8477 8.50517 23.8477 9.07575C23.8477 9.64633 24.3145 10.1132 24.8851 10.1132Z\" fill=\"currentColor\"/>\n</svg>\n"
																	}
																}
															}
														}
													],
													"fragmentStyle": {
														"height": "48px",
														"textColor": "colorBrandPrimary",
														"width": "48px"
													},
													"indexed": true
												},
												"id": "45073807-87c7-31c5-495a-0bb015ef1569",
												"type": "Fragment"
											},
											{
												"definition": {
													"fragment": {
														"key": "cp-text",
														"siteKey": "Customer Portal"
													},
													"fragmentConfig": {
														"textType": "h5",
														"truncateText": false
													},
													"fragmentFields": [
														{
															"id": "element-text",
															"value": {
																"fragmentLink": {
																},
																"text": {
																	"value_i18n": {
																		"en_US": "Release Notes"
																	}
																}
															}
														}
													],
													"fragmentStyle": {
														"marginBottom": "2",
														"marginTop": "2"
													},
													"indexed": true
												},
												"id": "14bc2ac2-af46-fe1a-cfa3-c6d3ba54c7a7",
												"type": "Fragment"
											},
											{
												"definition": {
													"fragment": {
														"key": "cp-text",
														"siteKey": "Customer Portal"
													},
													"fragmentConfig": {
														"textType": "text-paragraph",
														"truncateText": false
													},
													"fragmentFields": [
														{
															"id": "element-text",
															"value": {
																"fragmentLink": {
																},
																"text": {
																	"value_i18n": {
																		"en_US": "Review version highlights and technical details."
																	}
																}
															}
														}
													],
													"indexed": true
												},
												"id": "cf882d40-e3bd-8cc4-49cd-4d92081ae656",
												"type": "Fragment"
											}
										],
										"type": "Section"
									},
									{
										"definition": {
											"cssClasses": [
												"card",
												"card-flat"
											],
											"fragmentStyle": {
												"backgroundColor": "colorBrandPrimaryLighten5",
												"borderRadius": "borderRadiusLg",
												"paddingBottom": "4",
												"paddingLeft": "4",
												"paddingRight": "4",
												"paddingTop": "4",
												"textAlign": "center"
											},
											"indexed": true,
											"layout": {
												"align": "Center",
												"contentDisplay": "FlexColumn",
												"justify": "Center",
												"paddingBottom": 2,
												"paddingLeft": 2,
												"paddingRight": 2,
												"paddingTop": 2
											}
										},
										"id": "13c215d2-71c2-3471-32c9-36181fc640c1",
										"pageElements": [
											{
												"definition": {
													"fragment": {
														"key": "BASIC_COMPONENT-html"
													},
													"fragmentConfig": {
													},
													"fragmentFields": [
														{
															"id": "element-html",
															"value": {
																"html": {
																	"value_i18n": {
																		"en_US": "<svg width=\"48\" height=\"48\" viewBox=\"0 0 48 48\" fill=\"none\" xmlns=\"http://www.w3.org/2000/svg\">\n<g clip-path=\"url(#clip0_3059_9077)\">\n<path d=\"M24.3412 26.2541L26.0054 20.3409L24.3412 26.2541ZM42.6118 23.6907L43.5147 20.4828C43.7354 19.6987 43.6355 18.859 43.2371 18.1485C42.8387 17.438 42.1744 16.9148 41.3902 16.6941L20.6943 10.8692C19.9102 10.6485 19.0705 10.7484 18.36 11.1468C17.6495 11.5452 17.1264 12.2095 16.9057 12.9937L16.0028 16.2015C16.7824 16.7506 17.3726 17.5279 17.6918 18.4264C18.0111 19.3249 18.0439 20.3003 17.7855 21.2182C17.5272 22.1361 16.9905 22.9512 16.2494 23.5513C15.5084 24.1514 14.5994 24.5068 13.6479 24.5686L12.745 27.7764C12.5243 28.5606 12.6242 29.4002 13.0226 30.1108C13.421 30.8213 14.0853 31.3444 14.8695 31.5651L35.5653 37.39C36.3495 37.6107 37.1892 37.5109 37.8997 37.1125C38.6102 36.7141 39.1333 36.0497 39.354 35.2656L40.2569 32.0577C39.4773 31.5087 38.8871 30.7313 38.5678 29.8328C38.2486 28.9343 38.2158 27.9589 38.4742 27.0411C38.7325 26.1232 39.2692 25.308 40.0103 24.708C40.7513 24.1079 41.6603 23.7525 42.6118 23.6907Z\" fill=\"currentColor\"/>\n<path d=\"M24.3412 26.2541L26.0054 20.3409M42.6118 23.6907L43.5147 20.4828C43.7354 19.6987 43.6355 18.859 43.2371 18.1485C42.8387 17.438 42.1744 16.9148 41.3902 16.6941L20.6943 10.8692C19.9102 10.6485 19.0705 10.7484 18.36 11.1468C17.6495 11.5452 17.1264 12.2095 16.9057 12.9937L16.0028 16.2015C16.7824 16.7506 17.3726 17.5279 17.6918 18.4264C18.0111 19.3249 18.0439 20.3003 17.7855 21.2182C17.5272 22.1361 16.9905 22.9512 16.2494 23.5513C15.5084 24.1514 14.5994 24.5068 13.6479 24.5686L12.745 27.7764C12.5243 28.5606 12.6242 29.4002 13.0226 30.1108C13.421 30.8213 14.0853 31.3444 14.8695 31.5651L35.5653 37.39C36.3495 37.6107 37.1892 37.5109 37.8997 37.1125C38.6102 36.7141 39.1333 36.0497 39.354 35.2656L40.2569 32.0577C39.4773 31.5087 38.8871 30.7313 38.5678 29.8328C38.2486 28.9343 38.2158 27.9589 38.4742 27.041C38.7325 26.1232 39.2692 25.308 40.0103 24.708C40.7513 24.1079 41.6603 23.7525 42.6118 23.6907Z\" stroke=\"currentColor\" stroke-width=\"2\" stroke-linecap=\"round\" stroke-linejoin=\"round\"/>\n<path d=\"M32.3462 21.7083L30.5023 28.2596\" stroke=\"currentColor\" stroke-width=\"2\" stroke-linecap=\"round\"/>\n<path d=\"M18.3378 22.7201V16.3379V22.7201ZM35.889 15.0136V11.5512C35.889 10.7049 35.5528 9.89321 34.9543 9.29476C34.3559 8.69631 33.5442 8.36011 32.6978 8.36011H10.3601C9.51372 8.36011 8.70205 8.69631 8.1036 9.29476C7.50515 9.89321 7.16895 10.7049 7.16895 11.5512V15.0136C8.1032 15.3432 8.9122 15.9545 9.48443 16.7633C10.0567 17.572 10.364 18.5383 10.364 19.529C10.364 20.5197 10.0567 21.486 9.48443 22.2947C8.9122 23.1035 8.1032 23.7148 7.16895 24.0444V27.5068C7.16895 28.3531 7.50515 29.1648 8.1036 29.7632C8.70205 30.3617 9.51372 30.6979 10.3601 30.6979H32.6978C33.5442 30.6979 34.3559 30.3617 34.9543 29.7632C35.5528 29.1648 35.889 28.3531 35.889 27.5068V24.0444C34.9547 23.7148 34.1457 23.1035 33.5735 22.2947C33.0012 21.486 32.6939 20.5197 32.6939 19.529C32.6939 18.5383 33.0012 17.572 33.5735 16.7633C34.1457 15.9545 34.9547 15.3432 35.889 15.0136Z\" fill=\"#F0F5FF\"/>\n<path d=\"M18.3378 22.7201V16.3379M35.889 15.0136V11.5512C35.889 10.7049 35.5528 9.89321 34.9543 9.29476C34.3559 8.69631 33.5442 8.36011 32.6978 8.36011H10.3601C9.51372 8.36011 8.70205 8.69631 8.1036 9.29476C7.50515 9.89321 7.16895 10.7049 7.16895 11.5512V15.0136C8.1032 15.3432 8.9122 15.9545 9.48443 16.7633C10.0567 17.572 10.364 18.5383 10.364 19.529C10.364 20.5197 10.0567 21.486 9.48443 22.2947C8.9122 23.1035 8.1032 23.7148 7.16895 24.0444V27.5068C7.16895 28.3531 7.50515 29.1648 8.1036 29.7632C8.70205 30.3617 9.51372 30.6979 10.3601 30.6979H32.6978C33.5442 30.6979 34.3559 30.3617 34.9543 29.7632C35.5528 29.1648 35.889 28.3531 35.889 27.5068V24.0444C34.9547 23.7148 34.1457 23.1035 33.5735 22.2947C33.0012 21.486 32.6939 20.5197 32.6939 19.529C32.6939 18.5383 33.0012 17.572 33.5735 16.7633C34.1457 15.9545 34.9547 15.3432 35.889 15.0136Z\" stroke=\"currentColor\" stroke-width=\"2\" stroke-linecap=\"round\" stroke-linejoin=\"round\"/>\n<path d=\"M25.0645 15.9204V22.9915\" stroke=\"currentColor\" stroke-width=\"2\" stroke-linecap=\"round\"/>\n</g>\n<defs>\n<clipPath id=\"clip0_3059_9077\">\n<rect width=\"48\" height=\"48\" fill=\"white\" transform=\"translate(0 0.000976562)\"/>\n</clipPath>\n</defs>\n</svg>\n"
																	}
																}
															}
														}
													],
													"fragmentStyle": {
														"height": "48px",
														"textColor": "colorBrandPrimary",
														"width": "48px"
													},
													"indexed": true
												},
												"id": "f31ff773-68e5-d6bf-0e9e-262f2e242c62",
												"type": "Fragment"
											},
											{
												"definition": {
													"fragment": {
														"key": "cp-text",
														"siteKey": "Customer Portal"
													},
													"fragmentConfig": {
														"textType": "h5",
														"truncateText": false
													},
													"fragmentFields": [
														{
															"id": "element-text",
															"value": {
																"fragmentLink": {
																},
																"text": {
																	"value_i18n": {
																		"en_US": "My Tickets"
																	}
																}
															}
														}
													],
													"fragmentStyle": {
														"marginBottom": "2",
														"marginTop": "2"
													},
													"indexed": true
												},
												"id": "f2bc8afa-92af-abfc-2cb0-66b835312c38",
												"type": "Fragment"
											},
											{
												"definition": {
													"fragment": {
														"key": "cp-text",
														"siteKey": "Customer Portal"
													},
													"fragmentConfig": {
														"textType": "text-paragraph",
														"truncateText": false
													},
													"fragmentFields": [
														{
															"id": "element-text",
															"value": {
																"fragmentLink": {
																},
																"text": {
																	"value_i18n": {
																		"en_US": "Track open and closed support requests."
																	}
																}
															}
														}
													],
													"indexed": true
												},
												"id": "369019c6-8ecc-8c19-90b4-5f802b3a5424",
												"type": "Fragment"
											}
										],
										"type": "Section"
									},
									{
										"definition": {
											"cssClasses": [
												"card",
												"card-flat"
											],
											"fragmentStyle": {
												"backgroundColor": "colorBrandPrimaryLighten5",
												"borderRadius": "borderRadiusLg",
												"paddingBottom": "4",
												"paddingLeft": "4",
												"paddingRight": "4",
												"paddingTop": "4",
												"textAlign": "center"
											},
											"indexed": true,
											"layout": {
												"align": "Center",
												"contentDisplay": "FlexColumn",
												"justify": "Center",
												"paddingBottom": 2,
												"paddingLeft": 2,
												"paddingRight": 2,
												"paddingTop": 2
											}
										},
										"id": "4f6b3285-d30c-ae40-ef3d-a56900c3722e",
										"pageElements": [
											{
												"definition": {
													"fragment": {
														"key": "BASIC_COMPONENT-html"
													},
													"fragmentConfig": {
													},
													"fragmentFields": [
														{
															"id": "element-html",
															"value": {
																"html": {
																	"value_i18n": {
																		"en_US": "<svg width=\"48\" height=\"48\" viewBox=\"0 0 48 48\" fill=\"none\" xmlns=\"http://www.w3.org/2000/svg\">\n<path d=\"M9.4502 18.551C9.4502 10.511 15.9702 4.00098 24.0002 4.00098C32.0302 4.00098 38.5502 10.511 38.5502 18.551\" stroke=\"currentColor\" stroke-width=\"2\" stroke-linecap=\"round\" stroke-linejoin=\"round\"/>\n<path d=\"M38.55 33.0908V34.9108C38.55 39.9308 34.48 44.0008 29.46 44.0008\" stroke=\"currentColor\" stroke-width=\"2\" stroke-linecap=\"round\" stroke-linejoin=\"round\"/>\n<path d=\"M34.9102 18.551H38.5502C41.5602 18.551 44.0002 20.991 44.0002 24.001V27.641C44.0002 30.651 41.5602 33.091 38.5502 33.091H34.9102V18.541V18.551Z\" fill=\"currentColor\" stroke=\"currentColor\" stroke-width=\"2\" stroke-linecap=\"round\" stroke-linejoin=\"round\"/>\n<path d=\"M13.0898 33.0911H9.44984C6.43984 33.0911 3.99984 30.6511 3.99984 27.6411L3.99984 24.0011C3.99984 20.9911 6.43984 18.5511 9.44984 18.5511H13.0898L13.0898 33.1011V33.0911Z\" fill=\"currentColor\" stroke=\"currentColor\" stroke-width=\"2\" stroke-linecap=\"round\" stroke-linejoin=\"round\"/>\n<path d=\"M34.9098 22.181C34.9098 16.1556 30.0253 11.271 23.9998 11.271C17.9744 11.271 13.0898 16.1556 13.0898 22.181V29.451C13.0898 35.4764 17.9744 40.361 23.9998 40.361C30.0253 40.361 34.9098 35.4764 34.9098 29.451V22.181Z\" stroke=\"currentColor\" stroke-width=\"2\" stroke-linecap=\"round\" stroke-linejoin=\"round\"/>\n</svg>"
																	}
																}
															}
														}
													],
													"fragmentStyle": {
														"height": "48px",
														"textColor": "colorBrandPrimary",
														"width": "48px"
													},
													"indexed": true
												},
												"id": "ac81bc2c-12a6-0a87-16ba-cfdcd9b982a1",
												"type": "Fragment"
											},
											{
												"definition": {
													"fragment": {
														"key": "cp-text",
														"siteKey": "Customer Portal"
													},
													"fragmentConfig": {
														"textType": "h5",
														"truncateText": false
													},
													"fragmentFields": [
														{
															"id": "element-text",
															"value": {
																"fragmentLink": {
																},
																"text": {
																	"value_i18n": {
																		"en_US": "Submit a Ticket"
																	}
																}
															}
														}
													],
													"fragmentStyle": {
														"marginBottom": "2",
														"marginTop": "2"
													},
													"indexed": true
												},
												"id": "96847477-9ba3-bad0-dc40-c63510756869",
												"type": "Fragment"
											},
											{
												"definition": {
													"fragment": {
														"key": "cp-text",
														"siteKey": "Customer Portal"
													},
													"fragmentConfig": {
														"textType": "text-paragraph",
														"truncateText": false
													},
													"fragmentFields": [
														{
															"id": "element-text",
															"value": {
																"fragmentLink": {
																},
																"text": {
																	"value_i18n": {
																		"en_US": "Need help? Log an issue or ask a question."
																	}
																}
															}
														}
													],
													"indexed": true
												},
												"id": "ebfe7bbc-03e6-f390-67b9-ab1cdbe40ca8",
												"type": "Fragment"
											}
										],
										"type": "Section"
									}
								],
								"type": "FragmentDropZone"
							}
						],
						"type": "Fragment"
					},
					{
						"definition": {
							"fragmentStyle": {
								"backgroundColor": "colorBrandPrimary",
								"borderRadius": "borderRadiusLg",
								"paddingBottom": "3",
								"paddingLeft": "3",
								"paddingRight": "3",
								"paddingTop": "3",
								"textColor": "colorNeutral0"
							},
							"indexed": true,
							"layout": {
								"paddingBottom": 1,
								"paddingLeft": 1,
								"paddingRight": 1,
								"paddingTop": 1
							}
						},
						"id": "604d6cba-ab30-cc4f-1861-81d5adf4b7c9",
						"pageElements": [
							{
								"definition": {
									"fragment": {
										"key": "cp-layout",
										"siteKey": "Customer Portal"
									},
									"fragmentConfig": {
										"alignDesktop": "center",
										"alignMobile": "flex-start",
										"alignTablet": "flex-start",
										"directionDesktop": "row",
										"directionMobile": "row",
										"directionTablet": "row",
										"distributeDesktop": "space-between",
										"distributeMobile": "flex-start",
										"distributeTablet": "flex-start",
										"fillHeightDesktop": true,
										"fillHeightMobile": true,
										"fillHeightTablet": true,
										"horizontalGapDesktop": "var(--spacer-4)",
										"horizontalGapMobile": "var(--spacer-3)",
										"horizontalGapTablet": "var(--spacer-4)",
										"verticalGapDesktop": "var(--spacer-4)",
										"verticalGapMobile": "var(--spacer-3)",
										"verticalGapTablet": "var(--spacer-4)",
										"widthBasisDesktop": "1",
										"widthBasisMobile": "1",
										"widthBasisTablet": "1",
										"widthDesktop": "manual",
										"widthGrowDesktop": "0",
										"widthGrowMobile": "1",
										"widthGrowTablet": "1",
										"widthMobile": "manual",
										"widthTablet": "manual",
										"wrapDesktop": "nowrap",
										"wrapMobile": "nowrap",
										"wrapTablet": "nowrap"
									},
									"fragmentFields": [
									],
									"indexed": true
								},
								"id": "9839e38b-9ed9-dbf1-5e69-ffd42fe642de",
								"pageElements": [
									{
										"definition": {
										},
										"id": "5f4a1e60-1f34-d439-2016-7255849c55bd",
										"pageElements": [
											{
												"definition": {
													"indexed": true,
													"layout": {
														"align": "Center",
														"contentDisplay": "FlexRow",
														"justify": "Center"
													}
												},
												"id": "b39b712e-1d62-d096-960c-c1d32255e2f9",
												"pageElements": [
													{
														"definition": {
															"fragment": {
																"key": "BASIC_COMPONENT-html"
															},
															"fragmentConfig": {
															},
															"fragmentFields": [
																{
																	"id": "element-html",
																	"value": {
																		"html": {
																			"value_i18n": {
																				"en_US": "<svg width=\"48\" height=\"48\" viewBox=\"0 0 48 48\" fill=\"none\" xmlns=\"http://www.w3.org/2000/svg\">\n<path d=\"M24 40.361H4V4.00098H33.09V22.181\" stroke=\"white\" stroke-width=\"2\" stroke-linecap=\"round\" stroke-linejoin=\"round\"/>\n<path d=\"M9.4502 11.271H27.6402\" stroke=\"white\" stroke-width=\"2\" stroke-linecap=\"round\" stroke-linejoin=\"round\"/>\n<path d=\"M9.4502 18.551H27.6402\" stroke=\"white\" stroke-width=\"2\" stroke-linecap=\"round\" stroke-linejoin=\"round\"/>\n<path d=\"M9.4502 25.821H24.0002\" stroke=\"white\" stroke-width=\"2\" stroke-linecap=\"round\" stroke-linejoin=\"round\"/>\n<path d=\"M9.4502 33.0911H24.0002\" stroke=\"white\" stroke-width=\"2\" stroke-linecap=\"round\" stroke-linejoin=\"round\"/>\n<path d=\"M35.8198 25.821C40.84 25.821 44.9096 29.8907 44.9097 34.9109C44.9097 39.9312 40.8401 44.0007 35.8198 44.0007C30.7996 44.0006 26.73 39.9311 26.73 34.9109C26.7301 29.8907 30.7997 25.8211 35.8198 25.821ZM40.8501 31.9109C40.4912 31.4913 39.8597 31.4418 39.4399 31.8005L33.5854 36.8064L32.3677 35.0759C32.0499 34.6242 31.4258 34.515 30.9741 34.8328C30.5225 35.1505 30.4143 35.7746 30.7319 36.2263L32.5815 38.8562C32.7435 39.0865 32.9955 39.238 33.2749 39.2732C33.5543 39.3084 33.8353 39.2237 34.0493 39.0408L40.7397 33.321C41.1595 32.9621 41.209 32.3306 40.8501 31.9109Z\" fill=\"white\"/>\n</svg>\n"
																			}
																		}
																	}
																}
															],
															"fragmentStyle": {
																"height": "48px",
																"width": "48px"
															},
															"indexed": true
														},
														"id": "91bd3700-3f6a-2fbc-7f64-f7f4f9be0a38",
														"type": "Fragment"
													},
													{
														"definition": {
															"fragment": {
																"key": "cp-text",
																"siteKey": "Customer Portal"
															},
															"fragmentConfig": {
																"textType": "text-paragraph-lg",
																"truncateText": false
															},
															"fragmentFields": [
																{
																	"id": "element-text",
																	"value": {
																		"fragmentLink": {
																		},
																		"text": {
																			"value_i18n": {
																				"en_US": "Get the latest updates on products, security, and system improvements."
																			}
																		}
																	}
																}
															],
															"indexed": true
														},
														"id": "b1873f2e-ae6b-c777-5148-9d9353603b1a",
														"type": "Fragment"
													}
												],
												"type": "Section"
											},
											{
												"definition": {
													"fragment": {
														"key": "cp-button",
														"siteKey": "Customer Portal"
													},
													"fragmentConfig": {
														"iconLeft": true,
														"iconRight": false,
														"inverted": true,
														"size": "medium",
														"style": "neutral",
														"type": "ghost",
														"url": ""
													},
													"fragmentFields": [
														{
															"id": "button-text",
															"value": {
																"fragmentLink": {
																},
																"text": {
																	"value_i18n": {
																		"en_US": "Subscribe"
																	}
																}
															}
														},
														{
															"id": "link",
															"value": {
																"fragmentLink": {
																},
																"text": {
																	"value_i18n": {
																		"en_US": "Subscribe"
																	}
																}
															}
														},
														{
															"id": "button-icon-left",
															"value": {
																"html": {
																	"value_i18n": {
																		"en_US": "<svg width=\"16\" height=\"16\" viewBox=\"0 0 16 16\" fill=\"none\" xmlns=\"http://www.w3.org/2000/svg\">\n<mask id=\"mask0_3669_9000\" style=\"mask-type:alpha\" maskUnits=\"userSpaceOnUse\" x=\"0\" y=\"0\" width=\"16\" height=\"17\">\n<path d=\"M13.2406 2.33848L7.94375 8.5291L5.70625 6.28848C4.79688 5.38535 3.38437 6.80098 4.29375 7.7041L7.29375 10.7072C7.475 10.8885 7.725 11.001 8 11.001C8.30313 11.001 8.57501 10.8635 8.75938 10.651L14.7594 3.63848C15.5906 2.66973 14.0719 1.3791 13.2406 2.33848Z\" fill=\"currentColor\"/>\n<path d=\"M8 16.001C3.5875 16.001 0 12.4135 0 8.00098C0 3.58848 3.5875 0.000976562 8 0.000976562C8.85312 0.000976562 9.69375 0.135352 10.4969 0.397852C11.7688 0.813477 11.1219 2.70723 9.875 2.29785C9.27188 2.10098 8.64062 2.00098 8 2.00098C4.69063 2.00098 2 4.6916 2 8.00098C2 11.3104 4.69063 14.001 8 14.001C11.3094 14.001 14 11.3104 14 8.00098C14 7.77285 13.9875 7.55098 13.9625 7.33223C13.8844 5.97598 15.7875 5.83848 15.95 7.11348C15.9812 7.4041 16 7.70098 16 8.0041C16 12.4135 12.4125 16.001 8 16.001Z\" fill=\"currentColor\"/>\n</mask>\n<g mask=\"url(#mask0_3669_9000)\">\n<rect y=\"0.000976562\" width=\"16\" height=\"16\" fill=\"white\"/>\n</g>\n</svg>"
																	}
																}
															}
														}
													],
													"indexed": true
												},
												"id": "c67ece1a-d75c-1998-1edc-363db9982638",
												"type": "Fragment"
											}
										],
										"type": "FragmentDropZone"
									}
								],
								"type": "Fragment"
							}
						],
						"type": "Section"
					}
				],
				"type": "Section"
			}
		],
		"type": "Root"
	},
	"settings": {
		"colorSchemeName": "01",
		"masterPage": {
			"key": "home"
		},
		"themeName": "Dialect"
	},
	"version": 1.1
}