{
	"accountEntryRestricted": true,
	"accountEntryRestrictedObjectFieldName": "r_accToMDFReqs_accountEntryId",
	"enableComments": true,
	"externalReferenceCode": "cba46ee5-eaf7-d029-3112-d78b2c70a835",
	"label": {
		"en_US": "MDF Request"
	},
	"name": "MDFRequest",
	"objectActions": [
		{
			"active": true,
			"errorMessage": {
			},
			"externalReferenceCode": "MDF-REQUEST-STATUS-MANAGEMENT-ACTION",
			"label": {
				"en_US": "MDF Request Status Management"
			},
			"name": "mdfRequestStatusManagement",
			"objectActionExecutorKey": "function#liferay-partner-etc-spring-boot-object-action-mdf-request-status-management",
			"objectActionTriggerKey": "onAfterUpdate",
			"parameters": {
			},
			"status": {
				"code": 1,
				"label": "success",
				"label_i18n": "Success"
			},
			"system": false
		}
	],
	"objectFields": [
		{
			"DBType": "String",
			"businessType": "Text",
			"externalReferenceCode": "b3e0f842-d37f-1148-f27f-645507015916",
			"indexed": true,
			"indexedAsKeyword": false,
			"label": {
				"en_US": "External Reference Code SF"
			},
			"name": "externalReferenceCodeSF",
			"required": false,
			"type": "String"
		}
	],
	"panelCategoryKey": "control_panel.object",
	"pluralLabel": {
		"en_US": "MDF Requests"
	},
	"portlet": true,
	"scope": "company"
}